tether_agent/__init__.py
tether_agent/tether_agent.py
tether_agent-1.1.3.dist-info/METADATA
tether_agent-1.1.3.dist-info/WHEEL
tether_agent-1.1.3.dist-info/RECORD
