Metadata-Version: 2.3
Name: tether_agent
Version: 1.1.3
Summary: Standardised MQTT+MessagePack for inter-process communication
Author-email: Stephen Buchanan <stephen.buchanan@random.studio>
Requires-Python: >=3.11
Requires-Dist: msgpack==1.0.6
Requires-Dist: paho-mqtt==1.6.1
